{
  "schema_version": "phase2.v1",
  "sweep_id": "by_country_single_attempt_batch",
  "mh_level": "mh9",
  "granularity": "by_country",
  "scope_id": "COUNTRY_1/COUNTRY_1_2026-02-08",
  "dataset_name": "COUNTRY_1",
  "status": "complete",
  "cache_snapshot_path": "C:\\Users\\Administrator\\Desktop\\dippa\\src\\artifacts\\cache\\statistical_tuning\\mh9\\by_country\\COUNTRY_1_COUNTRY_1_2026-02-08\\template_cache.joblib",
  "attempt_seeds": [
    42
  ],
  "detector_families_requested": [
    "standard_zscore"
  ],
  "detectors": {
    "standard_zscore": {
      "threshold": 2.75
    }
  },
  "aggregate_metrics": {
    "standard_zscore": {
      "schema_version": "phase2.v1",
      "sweep_id": "by_country_single_attempt_batch",
      "run_id": "standard_zscore__threshold_2p750",
      "candidate_id": "standard_zscore__threshold_2p750",
      "experiment_family": "tuning",
      "detector_family": "standard_zscore",
      "dataset_name": "COUNTRY_1",
      "dataset_granularity": "by_country",
      "status": "ok",
      "error": "",
      "stage": "refine",
      "training_time_sec": 303.4075959000038,
      "n_train": 3224641,
      "n_eval_prices": 400178,
      "n_eval_products": 907367,
      "attempt_count": 1,
      "combined_precision": 0.4749569080133898,
      "combined_recall": 0.5413813741882324,
      "combined_f1": 0.5038979207004459,
      "weighted_f1_mean": 0.5038979207004459,
      "rank_score": 0.7069254372144069,
      "default_distance": 0.08333333333333333,
      "new_prices_accuracy_mean": 0.9008066410447351,
      "new_prices_accuracy_std": 0.0,
      "new_prices_precision_mean": 0.50328893610067,
      "new_prices_precision_std": 0.0,
      "new_prices_recall_mean": 0.6156633430791913,
      "new_prices_recall_std": 0.0,
      "new_prices_f1_mean": 0.5538333576863852,
      "new_prices_f1_std": 0.0,
      "new_prices_g_mean_mean": 0.7576932118466299,
      "new_prices_g_mean_std": 0.0,
      "new_products_accuracy_mean": 0.8835895508653059,
      "new_products_accuracy_std": 0.0,
      "new_products_precision_mean": 0.4088488424764027,
      "new_products_precision_std": 0.0,
      "new_products_recall_mean": 0.3680567801093282,
      "new_products_recall_std": 0.0,
      "new_products_f1_mean": 0.3873819010665878,
      "new_products_f1_std": 0.0,
      "new_products_g_mean_mean": 0.5884672964058867,
      "new_products_g_mean_std": 0.0,
      "threshold": 2.75
    }
  },
  "generated_at": "2026-03-23T04:30:44.456360+00:00"
}
