{
  "schema_version": "phase2.v1",
  "sweep_id": "all_global_single_attempt_batch",
  "experiment_family": "tuning",
  "detector_family": "modified_sn",
  "generated_at": "2026-03-25T04:26:10.861222+00:00",
  "candidate_count": 6,
  "rank_column": "rank_score",
  "best_candidate": {
    "schema_version": "phase2.v1",
    "sweep_id": "all_global_single_attempt_batch",
    "run_id": "modified_sn__threshold_3p000",
    "candidate_id": "modified_sn__threshold_3p000",
    "experiment_family": "tuning",
    "detector_family": "modified_sn",
    "dataset_name": "COUNTRY_1",
    "dataset_granularity": "by_country",
    "status": "ok",
    "error": "",
    "training_time_sec": 464.56689949985594,
    "n_train": 3318176,
    "n_eval_prices": 443352,
    "n_eval_products": 941418,
    "combined_precision": 0.2355275520395404,
    "combined_recall": 0.3309936194930398,
    "combined_f1": 0.2745138077111061,
    "stage": "coarse",
    "attempt_count": 1,
    "weighted_f1_mean": 0.2745138077111061,
    "rank_score": 0.5384342347825429,
    "default_distance": 0.5,
    "new_prices_accuracy_mean": 0.8292891427127881,
    "new_prices_accuracy_std": 0.0,
    "new_prices_precision_mean": 0.2289562871766496,
    "new_prices_precision_std": 0.0,
    "new_prices_recall_mean": 0.29865794519003047,
    "new_prices_recall_std": 0.0,
    "new_prices_f1_mean": 0.25920306948427574,
    "new_prices_f1_std": 0.0,
    "new_prices_g_mean_mean": 0.5150556119646692,
    "new_prices_g_mean_std": 0.0,
    "new_products_accuracy_mean": 0.8192705047067297,
    "new_products_accuracy_std": 0.0,
    "new_products_precision_mean": 0.2508605033862857,
    "new_products_precision_std": 0.0,
    "new_products_recall_mean": 0.40644352620006163,
    "new_products_recall_std": 0.0,
    "new_products_f1_mean": 0.31023886357371044,
    "new_products_f1_std": 0.0,
    "new_products_g_mean_mean": 0.592984354690915,
    "new_products_g_mean_std": 0.0,
    "threshold": 3.0
  }
}
