{
  "schema_version": "phase2.v1",
  "run_id": "hybrid_weighted__threshold_4p000__w_0p250",
  "experiment_family": "tuning",
  "dataset_splits": [
    "new_prices",
    "new_products"
  ],
  "generated_at": "2026-03-29T03:59:47.324909+00:00",
  "detector_count": 1,
  "candidate_count": 1,
  "split_summaries": {
    "new_prices": {
      "n_metric_rows": 1,
      "best_detector": "hybrid_weighted",
      "best_candidate_id": "hybrid_weighted__threshold_4p000__w_0p250",
      "best_f1": 0.3947869038480793,
      "total_rows": 357112,
      "total_injected": 35711
    },
    "new_products": {
      "n_metric_rows": 1,
      "best_detector": "hybrid_weighted",
      "best_candidate_id": "hybrid_weighted__threshold_4p000__w_0p250",
      "best_f1": 0.3391129849596627,
      "total_rows": 1295799,
      "total_injected": 129579
    }
  },
  "anomaly_types": [
    "decimal_shift",
    "list_price_violation",
    "price_drop",
    "price_spike"
  ]
}
