{
  "schema_version": "phase2.v1",
  "sweep_id": "by_competitor_single_attempt_batch",
  "mh_level": "mh28",
  "granularity": "by_competitor",
  "scope_id": "COUNTRY_3/B2C/COMPETITOR_2_COUNTRY_3_2026-02-08",
  "dataset_name": "COMPETITOR_2_COUNTRY_3",
  "detector_family": "standard_zscore",
  "cache_snapshot_path": "C:\\Users\\Administrator\\Desktop\\dippa\\src\\artifacts\\cache\\statistical_tuning\\mh28\\by_competitor\\COUNTRY_3_B2C_COMPETITOR_2_COUNTRY_3_2026-02-08\\template_cache.joblib",
  "attempt_seeds": [
    42
  ],
  "best_candidate": {
    "schema_version": "phase2.v1",
    "sweep_id": "by_competitor_single_attempt_batch",
    "run_id": "standard_zscore__threshold_2p750",
    "candidate_id": "standard_zscore__threshold_2p750",
    "experiment_family": "tuning",
    "detector_family": "standard_zscore",
    "dataset_name": "COMPETITOR_2_COUNTRY_3",
    "dataset_granularity": "by_competitor",
    "status": "ok",
    "error": "",
    "stage": "refine",
    "training_time_sec": 61.31991610000841,
    "n_train": 652261,
    "n_eval_prices": 41960,
    "n_eval_products": 173666,
    "attempt_count": 1,
    "combined_precision": 0.4571286634728184,
    "combined_recall": 0.8408024094504596,
    "combined_f1": 0.5918442226040029,
    "weighted_f1_mean": 0.5918442226040029,
    "rank_score": 0.8626720360817791,
    "default_distance": 0.08333333333333333,
    "new_prices_accuracy_mean": 0.9024070543374643,
    "new_prices_accuracy_std": 0.0,
    "new_prices_precision_mean": 0.506748630228518,
    "new_prices_precision_std": 0.0,
    "new_prices_recall_mean": 0.90371782650143,
    "new_prices_recall_std": 0.0,
    "new_prices_f1_mean": 0.6493706652966863,
    "new_prices_f1_std": 0.0,
    "new_prices_g_mean_mean": 0.9029893261161718,
    "new_prices_g_mean_std": 0.0,
    "new_products_accuracy_mean": 0.8354945700367372,
    "new_products_accuracy_std": 0.0,
    "new_products_precision_mean": 0.3413487410428527,
    "new_products_precision_std": 0.0,
    "new_products_recall_mean": 0.6939997696648623,
    "new_products_recall_std": 0.0,
    "new_products_f1_mean": 0.4576158563210753,
    "new_products_f1_std": 0.0,
    "new_products_g_mean_mean": 0.768598359334863,
    "new_products_g_mean_std": 0.0,
    "threshold": 2.75
  },
  "configuration": {
    "threshold": 2.75
  },
  "generated_at": "2026-03-22T18:41:07.576373+00:00"
}
