{
  "schema_version": "phase2.v1",
  "sweep_id": "1-6coarse_grid_single_attempt_batch",
  "mh_level": "mh20",
  "granularity": "by_competitor",
  "scope_id": "COUNTRY_4/B2B/COMPETITOR_1_COUNTRY_4_2026-02-08",
  "dataset_name": "COMPETITOR_1_COUNTRY_4",
  "detector_family": "modified_mad",
  "cache_snapshot_path": "C:\\Users\\Administrator\\Desktop\\dippa\\src\\artifacts\\cache\\statistical_tuning\\mh20\\by_competitor\\COUNTRY_4_B2B_COMPETITOR_1_COUNTRY_4_2026-02-08\\template_cache.joblib",
  "attempt_seeds": [
    42
  ],
  "best_candidate": {
    "schema_version": "phase2.v1",
    "sweep_id": "1-6coarse_grid_single_attempt_batch",
    "run_id": "modified_mad__threshold_5p500",
    "candidate_id": "modified_mad__threshold_5p500",
    "experiment_family": "tuning",
    "detector_family": "modified_mad",
    "dataset_name": "COMPETITOR_1_COUNTRY_4",
    "dataset_granularity": "by_competitor",
    "status": "ok",
    "error": "",
    "stage": "refine",
    "training_time_sec": 15.817416299832985,
    "n_train": 172386,
    "n_eval_prices": 12296,
    "n_eval_products": 46200,
    "attempt_count": 1,
    "combined_precision": 0.3137133198292921,
    "combined_recall": 0.8064536683820653,
    "combined_f1": 0.4512198908429351,
    "weighted_f1_mean": 0.4512198908429351,
    "rank_score": 0.8040479119733399,
    "default_distance": 0.7,
    "new_prices_accuracy_mean": 0.819128171763175,
    "new_prices_accuracy_std": 0.0,
    "new_prices_precision_mean": 0.33531943065210196,
    "new_prices_precision_std": 0.0,
    "new_prices_recall_mean": 0.8242473555736372,
    "new_prices_recall_std": 0.0,
    "new_prices_f1_mean": 0.4767058823529412,
    "new_prices_f1_std": 0.0,
    "new_prices_g_mean_mean": 0.8213985958205734,
    "new_prices_g_mean_std": 0.0,
    "new_products_accuracy_mean": 0.7624675324675325,
    "new_products_accuracy_std": 0.0,
    "new_products_precision_mean": 0.26329906124273583,
    "new_products_precision_std": 0.0,
    "new_products_recall_mean": 0.7649350649350649,
    "new_products_recall_std": 0.0,
    "new_products_f1_mean": 0.3917525773195877,
    "new_products_f1_std": 0.0,
    "new_products_g_mean_mean": 0.7635629829964617,
    "new_products_g_mean_std": 0.0,
    "threshold": 5.5
  },
  "configuration": {
    "threshold": 5.5
  },
  "generated_at": "2026-03-28T03:12:14.842147+00:00"
}
