{
  "schema_version": "phase2.v1",
  "sweep_id": "1-6coarse_grid_single_attempt_batch",
  "experiment_family": "tuning",
  "detector_family": "hybrid_avg",
  "generated_at": "2026-03-28T06:55:23.150531+00:00",
  "candidate_count": 10,
  "rank_column": "rank_score",
  "best_candidate": {
    "schema_version": "phase2.v1",
    "sweep_id": "1-6coarse_grid_single_attempt_batch",
    "run_id": "hybrid_avg__threshold_4p500",
    "candidate_id": "hybrid_avg__threshold_4p500",
    "experiment_family": "tuning",
    "detector_family": "hybrid_avg",
    "dataset_name": "COMPETITOR_1_COUNTRY_2",
    "dataset_granularity": "by_competitor",
    "status": "ok",
    "error": "",
    "training_time_sec": 47.450360500020906,
    "n_train": 282269,
    "n_eval_prices": 18456,
    "n_eval_products": 75178,
    "combined_precision": 0.34706612132907005,
    "combined_recall": 0.753629500323206,
    "combined_f1": 0.4752492493832512,
    "stage": "refine",
    "attempt_count": 1,
    "weighted_f1_mean": 0.4752492493832512,
    "rank_score": 0.7966127472541777,
    "default_distance": 0.5,
    "new_prices_accuracy_mean": 0.8396185522323364,
    "new_prices_accuracy_std": 0.0,
    "new_prices_precision_mean": 0.35988941945212366,
    "new_prices_precision_std": 0.0,
    "new_prices_recall_mean": 0.7761517615176152,
    "new_prices_recall_std": 0.0,
    "new_prices_f1_mean": 0.4917582417582418,
    "new_prices_f1_std": 0.0,
    "new_prices_g_mean_mean": 0.8106434230010973,
    "new_prices_g_mean_std": 0.0,
    "new_products_accuracy_mean": 0.8191758227140918,
    "new_products_accuracy_std": 0.0,
    "new_products_precision_mean": 0.3171450923752783,
    "new_products_precision_std": 0.0,
    "new_products_recall_mean": 0.7010775575362511,
    "new_products_recall_std": 0.0,
    "new_products_f1_mean": 0.4367282671749399,
    "new_products_f1_std": 0.0,
    "new_products_g_mean_mean": 0.7638745038446989,
    "new_products_g_mean_std": 0.0,
    "threshold": 4.5
  }
}
