{
  "schema_version": "phase2.v1",
  "run_id": "standard_zscore__threshold_2p500",
  "experiment_family": "tuning",
  "dataset_splits": [
    "new_prices",
    "new_products"
  ],
  "generated_at": "2026-03-22T21:52:01.404612+00:00",
  "detector_count": 1,
  "candidate_count": 1,
  "split_summaries": {
    "new_prices": {
      "n_metric_rows": 1,
      "best_detector": "standard_zscore",
      "best_candidate_id": "standard_zscore__threshold_2p500",
      "best_f1": 0.7361697171679165,
      "total_rows": 462416,
      "total_injected": 46241
    },
    "new_products": {
      "n_metric_rows": 1,
      "best_detector": "standard_zscore",
      "best_candidate_id": "standard_zscore__threshold_2p500",
      "best_f1": 0.3910164241946373,
      "total_rows": 791346,
      "total_injected": 79134
    }
  },
  "anomaly_types": [
    "decimal_shift",
    "list_price_violation",
    "price_drop",
    "price_spike"
  ]
}
