{
  "schema_version": "phase2.v1",
  "sweep_id": "1-6coarse_grid_single_attempt_batch",
  "experiment_family": "tuning",
  "detector_family": "modified_mad",
  "generated_at": "2026-03-28T12:25:27.576555+00:00",
  "candidate_count": 10,
  "rank_column": "rank_score",
  "best_candidate": {
    "schema_version": "phase2.v1",
    "sweep_id": "1-6coarse_grid_single_attempt_batch",
    "run_id": "modified_mad__threshold_3p500",
    "candidate_id": "modified_mad__threshold_3p500",
    "experiment_family": "tuning",
    "detector_family": "modified_mad",
    "dataset_name": "COUNTRY_3",
    "dataset_granularity": "by_country",
    "status": "ok",
    "error": "",
    "training_time_sec": 94.38534369994886,
    "n_train": 1029321,
    "n_eval_prices": 64470,
    "n_eval_products": 273928,
    "combined_precision": 0.30795438588031526,
    "combined_recall": 0.7632609234045683,
    "combined_f1": 0.4385265854169356,
    "stage": "refine",
    "attempt_count": 1,
    "weighted_f1_mean": 0.4385265854169356,
    "rank_score": 0.7852100133959956,
    "default_distance": 0.3,
    "new_prices_accuracy_mean": 0.8170777105630526,
    "new_prices_accuracy_std": 0.0,
    "new_prices_precision_mean": 0.32647364320955596,
    "new_prices_precision_std": 0.0,
    "new_prices_recall_mean": 0.7800527377074609,
    "new_prices_recall_std": 0.0,
    "new_prices_f1_mean": 0.4602992998032127,
    "new_prices_f1_std": 0.0,
    "new_prices_g_mean_mean": 0.8003578905603299,
    "new_prices_g_mean_std": 0.0,
    "new_products_accuracy_mean": 0.7713194708098479,
    "new_products_accuracy_std": 0.0,
    "new_products_precision_mean": 0.26474278544542035,
    "new_products_precision_std": 0.0,
    "new_products_recall_mean": 0.724080023364486,
    "new_products_recall_std": 0.0,
    "new_products_f1_mean": 0.38772358518228917,
    "new_products_f1_std": 0.0,
    "new_products_g_mean_mean": 0.7498649666792158,
    "new_products_g_mean_std": 0.0,
    "threshold": 3.5
  }
}
