{
  "schema_version": "phase2.v1",
  "run_id": "hybrid_weighted__threshold_3p000__w_0p900",
  "experiment_family": "tuning",
  "dataset_splits": [
    "new_prices",
    "new_products"
  ],
  "generated_at": "2026-03-25T15:49:15.172689+00:00",
  "detector_count": 1,
  "candidate_count": 1,
  "split_summaries": {
    "new_prices": {
      "n_metric_rows": 1,
      "best_detector": "hybrid_weighted",
      "best_candidate_id": "hybrid_weighted__threshold_3p000__w_0p900",
      "best_f1": 0.3734032099574189,
      "total_rows": 74224,
      "total_injected": 7422
    },
    "new_products": {
      "n_metric_rows": 1,
      "best_detector": "hybrid_weighted",
      "best_candidate_id": "hybrid_weighted__threshold_3p000__w_0p900",
      "best_f1": 0.33491392830126016,
      "total_rows": 244358,
      "total_injected": 24435
    }
  },
  "anomaly_types": [
    "decimal_shift",
    "price_drop",
    "price_spike"
  ]
}
