{
  "schema_version": "phase2.v1",
  "run_id": "iqr__multiplier_3p000",
  "experiment_family": "tuning",
  "dataset_splits": [
    "new_prices",
    "new_products"
  ],
  "generated_at": "2026-03-25T03:27:02.160510+00:00",
  "detector_count": 1,
  "candidate_count": 1,
  "split_summaries": {
    "new_prices": {
      "n_metric_rows": 1,
      "best_detector": "iqr",
      "best_candidate_id": "iqr__multiplier_3p000",
      "best_f1": 0.4857685009487667,
      "total_rows": 1454,
      "total_injected": 145
    },
    "new_products": {
      "n_metric_rows": 1,
      "best_detector": "iqr",
      "best_candidate_id": "iqr__multiplier_3p000",
      "best_f1": 0.39053254437869817,
      "total_rows": 1188,
      "total_injected": 118
    }
  },
  "anomaly_types": [
    "decimal_shift",
    "list_price_violation",
    "price_drop",
    "price_spike"
  ]
}
