{
  "schema_version": "phase2.v1",
  "sweep_id": "1-6coarse_grid_single_attempt_batch",
  "experiment_family": "tuning",
  "detector_family": "modified_sn",
  "generated_at": "2026-03-25T19:23:59.969027+00:00",
  "candidate_count": 10,
  "rank_column": "rank_score",
  "best_candidate": {
    "schema_version": "phase2.v1",
    "sweep_id": "1-6coarse_grid_single_attempt_batch",
    "run_id": "modified_sn__threshold_4p000",
    "candidate_id": "modified_sn__threshold_4p000",
    "experiment_family": "tuning",
    "detector_family": "modified_sn",
    "dataset_name": "COMPETITOR_1_COUNTRY_1",
    "dataset_granularity": "by_competitor",
    "status": "ok",
    "error": "",
    "training_time_sec": 19.289964499883354,
    "n_train": 99162,
    "n_eval_prices": 18662,
    "n_eval_products": 29065,
    "combined_precision": 0.3015879816124903,
    "combined_recall": 0.7321236544267726,
    "combined_f1": 0.4271960474611137,
    "stage": "coarse",
    "attempt_count": 1,
    "weighted_f1_mean": 0.4271960474611137,
    "rank_score": 0.7702495619732771,
    "default_distance": 0.4,
    "new_prices_accuracy_mean": 0.8114885864323224,
    "new_prices_accuracy_std": 0.0,
    "new_prices_precision_mean": 0.3181417877586966,
    "new_prices_precision_std": 0.0,
    "new_prices_recall_mean": 0.7743837084673098,
    "new_prices_recall_std": 0.0,
    "new_prices_f1_mean": 0.45099875156054936,
    "new_prices_f1_std": 0.0,
    "new_prices_g_mean_mean": 0.7947299932824807,
    "new_prices_g_mean_std": 0.0,
    "new_products_accuracy_mean": 0.7858248752795458,
    "new_products_accuracy_std": 0.0,
    "new_products_precision_mean": 0.26296243393800883,
    "new_products_precision_std": 0.0,
    "new_products_recall_mean": 0.6335168616655196,
    "new_products_recall_std": 0.0,
    "new_products_f1_mean": 0.37165640456243054,
    "new_products_f1_std": 0.0,
    "new_products_g_mean_mean": 0.7131285555851355,
    "new_products_g_mean_std": 0.0,
    "threshold": 4.0
  }
}
