{
  "schema_version": "phase2.v1",
  "sweep_id": "by_country_single_attempt_batch",
  "mh_level": "mh22",
  "granularity": "by_country",
  "scope_id": "COUNTRY_1/COUNTRY_1_2026-02-08",
  "dataset_name": "COUNTRY_1",
  "detector_family": "standard_zscore",
  "family_output_dir": "C:\\Users\\Administrator\\Desktop\\dippa\\src\\results\\tuning\\statistical\\by_country_single_attempt_batch\\mh22\\by_country\\COUNTRY_1_COUNTRY_1_2026-02-08\\standard_zscore",
  "cache_snapshot_path": "C:\\Users\\Administrator\\Desktop\\dippa\\src\\artifacts\\cache\\statistical_tuning\\mh22\\by_country\\COUNTRY_1_COUNTRY_1_2026-02-08\\template_cache.joblib",
  "attempt_seeds": [
    42
  ],
  "status": "complete",
  "completed_stage": "finalized",
  "active_stage": "idle",
  "started_at": "2026-03-23T03:01:50.223496+00:00",
  "updated_at": "2026-03-23T03:14:51.618373+00:00",
  "completed_at": "2026-03-23T03:14:51.618373+00:00",
  "error": "",
  "candidate_count": 9,
  "candidate_ids": [
    "standard_zscore__threshold_2p000",
    "standard_zscore__threshold_2p500",
    "standard_zscore__threshold_2p750",
    "standard_zscore__threshold_3p000",
    "standard_zscore__threshold_3p250",
    "standard_zscore__threshold_3p500",
    "standard_zscore__threshold_4p000",
    "standard_zscore__threshold_4p500",
    "standard_zscore__threshold_5p000"
  ],
  "best_candidate_id": "standard_zscore__threshold_3p000"
}
